export_nb/__init__.py
export_nb/_modidx.py
export_nb/core.py
export_nb-0.0.7.dist-info/LICENSE
export_nb-0.0.7.dist-info/METADATA
export_nb-0.0.7.dist-info/WHEEL
export_nb-0.0.7.dist-info/entry_points.txt
export_nb-0.0.7.dist-info/top_level.txt
export_nb-0.0.7.dist-info/RECORD
